{
  "collectionName": "components_account_delete_modals",
  "info": {
    "displayName": "deleteModal",
    "icon": "align-justify",
    "description": ""
  },
  "options": {},
  "attributes": {
    "title": {
      "type": "string",
      "default": "Delete account"
    },
    "content": {
      "type": "text",
      "default": "Are you sure you want to delete your account? This operation is irreversible."
    },
    "yes": {
      "type": "string",
      "default": "Yes"
    },
    "no": {
      "type": "string",
      "default": "No"
    }
  }
}
